aware_sdk/__init__.py
aware_sdk/cli.py
aware_sdk/configs/__init__.py
aware_sdk/configs/manifests/__init__.py
aware_sdk/configs/manifests/oss/manifest.json
aware_sdk/configs/manifests/oss/runtime.json
aware_sdk/configs/manifests/oss/stable.json
aware_sdk-0.7.0.dist-info/METADATA
aware_sdk-0.7.0.dist-info/WHEEL
aware_sdk-0.7.0.dist-info/entry_points.txt
aware_sdk-0.7.0.dist-info/licenses/LICENSE
aware_sdk-0.7.0.dist-info/RECORD
