Metadata-Version: 2.4
Name: aware-sdk
Version: 0.7.0
Summary: Infrastructure bundle for the Aware CLI stack (release, environment, terminal)
Project-URL: Homepage, https://github.com/aware-network/aware-sdk
Project-URL: Documentation, https://github.com/aware-network/aware-sdk/blob/main/README.md
Project-URL: Changelog, https://github.com/aware-network/aware-sdk/blob/main/CHANGELOG.md
Project-URL: Source, https://github.com/aware-network/aware-sdk
Project-URL: Issues, https://github.com/aware-network/aware-sdk/issues
Author: Aware OSS Team
License: MIT License
License-File: LICENSE
Keywords: automation,aware,release,sdk
Classifier: Development Status :: 3 - Alpha
Classifier: Intended Audience :: Developers
Classifier: License :: OSI Approved :: MIT License
Classifier: Operating System :: OS Independent
Classifier: Programming Language :: Python :: 3
Classifier: Programming Language :: Python :: 3 :: Only
Classifier: Programming Language :: Python :: 3.12
Classifier: Topic :: Software Development :: Build Tools
Requires-Python: >=3.12
Requires-Dist: aware-environment>=0.1.2
Requires-Dist: aware-file-system>=0.1.1
Requires-Dist: aware-release>=0.1.2
Requires-Dist: aware-terminal-providers>=0.1.1
Requires-Dist: aware-terminal>=0.3.3
Requires-Dist: aware-test-runner>=0.2.0
Provides-Extra: test
Requires-Dist: aware-file-system[test]>=0.1.1; extra == 'test'
Requires-Dist: pytest-asyncio>=0.23.7; extra == 'test'
Requires-Dist: pytest-mock>=3.12; extra == 'test'
Requires-Dist: pytest>=8.4.2; extra == 'test'
